whatinstalled/VERSION.md
whatinstalled/__init__.py
whatinstalled/linux.py
whatinstalled/lua.py
whatinstalled/mac.py
whatinstalled/main.py
whatinstalled/node.py
whatinstalled/python.py
whatinstalled/ruby.py
whatinstalled-0.3.0.dist-info/METADATA
whatinstalled-0.3.0.dist-info/WHEEL
whatinstalled-0.3.0.dist-info/entry_points.txt
whatinstalled-0.3.0.dist-info/licenses/LICENSE
whatinstalled-0.3.0.dist-info/RECORD
