Metadata-Version: 2.3
Name: whatinstalled
Version: 0.3.0
Summary: List all packages ever installed on your machine.
Project-URL: Homepage, https://github.com/AlexMili/WhatInstalled
Project-URL: Issues, https://github.com/AlexMili/WhatInstalled/issues
Project-URL: Repository, https://github.com/AlexMili/WhatInstalled
Project-URL: Documentation, https://github.com/AlexMili/WhatInstalled
Author: Alex Mili
License: MIT License
License-File: LICENSE
Classifier: Intended Audience :: Developers
Classifier: License :: OSI Approved :: MIT License
Requires-Python: >=3.8
Requires-Dist: tabulate
Requires-Dist: typer
